main.py
style/global.tcss
yamp_py/__init__.py
yamp_py/fetch.py
yamp_py/layout.py
yamp_py/player.py
yamp_py/utils.py
yamp_py-0.1.2.dist-info/LICENSE
yamp_py-0.1.2.dist-info/METADATA
yamp_py-0.1.2.dist-info/WHEEL
yamp_py-0.1.2.dist-info/entry_points.txt
yamp_py-0.1.2.dist-info/RECORD
