Metadata-Version: 2.1
Name: yamp_py
Version: 0.1.2
Summary: 
Home-page: https://github.com/NurAlam123/yamp
License: MIT
Author: Nur Alam
Author-email: nuralam.rsc@gmail.com
Requires-Python: >=3.12,<4.0
Classifier: License :: OSI Approved :: MIT License
Classifier: Programming Language :: Python :: 3
Classifier: Programming Language :: Python :: 3.12
Requires-Dist: numpy (>=1.26.4,<2.0.0)
Requires-Dist: pydub (>=0.25.1,<0.26.0)
Requires-Dist: pyfiglet (>=1.0.2,<2.0.0)
Requires-Dist: requests (>=2.32.2,<3.0.0)
Requires-Dist: sounddevice (>=0.4.6,<0.5.0)
Requires-Dist: textual (>=0.62.0,<0.63.0)
Requires-Dist: wheel (>=0.43.0,<0.44.0)
Project-URL: Repository, https://github.com/NurAlam123/yamp
